py_gardener
py_gardener/resources
py_gardener/resources/docker
py_gardener/resources/docker/lambda
py_gardener/resources/docker/lambda-pg10
py_gardener/resources/docker/lambda-pg10-postgis
