Metadata-Version: 2.1
Name: py-gardener
Version: 0.6.8
Summary: Basic Tests for python project to enforce best practices.
Home-page: https://github.com/loopmediagroup/py-gardener
Author: Lukas Siemon
Author-email: lukas.siemon@getintheloop.ca
Maintainer: Lukas Siemon
Maintainer-email: lukas.siemon@getintheloop.ca
License: MIT
Keywords: Python,Testing,Best Practices
Platform: any
